httprama-0.0.2.dist-info/RECORD
httprama-0.0.2.dist-info/METADATA
httprama-0.0.2.dist-info/top_level.txt
httprama-0.0.2.dist-info/WHEEL
httprama/response.cpython-38-x86_64-linux-gnu.so
httprama/_version.cpython-38-x86_64-linux-gnu.so
httprama/__init__.py
httprama/exceptions.cpython-38-x86_64-linux-gnu.so
httprama/filepost.cpython-38-x86_64-linux-gnu.so
httprama/__init__.cpython-38-x86_64-linux-gnu.so
httprama/request.cpython-38-x86_64-linux-gnu.so
httprama/poolmanager.cpython-38-x86_64-linux-gnu.so
httprama/connection.cpython-38-x86_64-linux-gnu.so
httprama/fields.cpython-38-x86_64-linux-gnu.so
httprama/connectionpool.cpython-38-x86_64-linux-gnu.so
httprama/_collections.cpython-38-x86_64-linux-gnu.so
httprama/util/response.cpython-38-x86_64-linux-gnu.so
httprama/util/__init__.py
httprama/util/queue.cpython-38-x86_64-linux-gnu.so
httprama/util/url.cpython-38-x86_64-linux-gnu.so
httprama/util/ssl_.cpython-38-x86_64-linux-gnu.so
httprama/util/timeout.cpython-38-x86_64-linux-gnu.so
httprama/util/__init__.cpython-38-x86_64-linux-gnu.so
httprama/util/request.cpython-38-x86_64-linux-gnu.so
httprama/util/wait.cpython-38-x86_64-linux-gnu.so
httprama/util/connection.cpython-38-x86_64-linux-gnu.so
httprama/util/retry.cpython-38-x86_64-linux-gnu.so
httprama/contrib/appengine.cpython-38-x86_64-linux-gnu.so
httprama/contrib/ssl.cpython-38-x86_64-linux-gnu.so
httprama/contrib/socks.cpython-38-x86_64-linux-gnu.so
httprama/contrib/pyopenssl.cpython-38-x86_64-linux-gnu.so
httprama/contrib/__init__.py
httprama/contrib/securetransport.cpython-38-x86_64-linux-gnu.so
httprama/contrib/ntlmpool.cpython-38-x86_64-linux-gnu.so
httprama/contrib/__init__.cpython-38-x86_64-linux-gnu.so
httprama/contrib/_appengine_environ.cpython-38-x86_64-linux-gnu.so
httprama/contrib/_securetransport/bindings.cpython-38-x86_64-linux-gnu.so
httprama/contrib/_securetransport/__init__.py
httprama/contrib/_securetransport/low_level.cpython-38-x86_64-linux-gnu.so
httprama/contrib/_securetransport/__init__.cpython-38-x86_64-linux-gnu.so
httprama/packages/__init__.py
