Metadata-Version: 2.1
Name: httprama
Version: 0.0.2
Summary: UNKNOWN
Home-page: UNKNOWN
License: UNKNOWN
Platform: UNKNOWN
Classifier: Environment :: Web Environment
Classifier: Intended Audience :: Developers
Classifier: Programming Language :: Python :: 3.5
Classifier: Programming Language :: Python :: 3.6
Classifier: Programming Language :: Python :: 3.7
Classifier: Programming Language :: Python :: 3.8
Classifier: Programming Language :: Python :: Implementation :: PyPy
Classifier: Topic :: Internet :: WWW/HTTP
Classifier: Topic :: Software Development :: Libraries
Provides-Extra: brotli
Requires-Dist: brotlipy (>=0.6.0) ; extra == 'brotli'
Provides-Extra: secure
Requires-Dist: pyOpenSSL (>=0.14) ; extra == 'secure'
Requires-Dist: cryptography (>=1.3.4) ; extra == 'secure'
Requires-Dist: idna (>=2.0.0) ; extra == 'secure'
Requires-Dist: certifi ; extra == 'secure'
Requires-Dist: ipaddress ; (python_version == "3.5") and extra == 'secure'
Provides-Extra: socks
Requires-Dist: PySocks (!=1.5.7,<2.0,>=1.5.6) ; extra == 'socks'
